{
    "sourceFile": ".env",
    "activeCommit": 0,
    "commits": [
        {
            "activePatchIndex": 16,
            "patches": [
                {
                    "date": 1751212334419,
                    "content": "Index: \n===================================================================\n--- \n+++ \n"
                },
                {
                    "date": 1751212381605,
                    "content": "Index: \n===================================================================\n--- \n+++ \n@@ -1,3 +1,3 @@\n PORT=5000\r\n-MONGO_URI=mongodb://localhost:27017/admin-auth\r\n+MONGO_URI=mongodb://localhost:27017/mvp\r\n JWT_SECRET=your_jwt_secret\n\\ No newline at end of file\n"
                },
                {
                    "date": 1753205731137,
                    "content": "Index: \n===================================================================\n--- \n+++ \n@@ -1,3 +1,5 @@\n PORT=5000\r\n MONGO_URI=mongodb://localhost:27017/mvp\r\n-JWT_SECRET=your_jwt_secret\n\\ No newline at end of file\n+JWT_SECRET=your_jwt_secret\r\n+ADMIN_EMAIL=yourgmail@gmail.com\r\n+ADMIN_PASS=your_app_password_here\n\\ No newline at end of file\n"
                },
                {
                    "date": 1753207491324,
                    "content": "Index: \n===================================================================\n--- \n+++ \n@@ -1,5 +1,5 @@\n PORT=5000\r\n MONGO_URI=mongodb://localhost:27017/mvp\r\n JWT_SECRET=your_jwt_secret\r\n ADMIN_EMAIL=yourgmail@gmail.com\r\n-ADMIN_PASS=your_app_password_here\n\\ No newline at end of file\n+ADMIN_PASS=abcdefgijklmnop\n\\ No newline at end of file\n"
                },
                {
                    "date": 1753207497091,
                    "content": "Index: \n===================================================================\n--- \n+++ \n@@ -0,0 +1,5 @@\n+PORT=5000\r\n+MONGO_URI=mongodb://localhost:27017/mvp\r\n+JWT_SECRET=your_jwt_secret\r\n+ADMIN_EMAIL=devsenior@gmail.com\r\n+ADMIN_PASS=abcdefgijklmnop\n\\ No newline at end of file\n"
                },
                {
                    "date": 1753207502944,
                    "content": "Index: \n===================================================================\n--- \n+++ \n@@ -0,0 +1,5 @@\n+PORT=5000\r\n+MONGO_URI=mongodb://localhost:27017/mvp\r\n+JWT_SECRET=your_jwt_secret\r\n+ADMIN_EMAIL=devsenior477@gmail.com\r\n+ADMIN_PASS=\n\\ No newline at end of file\n"
                },
                {
                    "date": 1753207510570,
                    "content": "Index: \n===================================================================\n--- \n+++ \n@@ -0,0 +1,5 @@\n+PORT=5000\r\n+MONGO_URI=mongodb://localhost:27017/mvp\r\n+JWT_SECRET=your_jwt_secret\r\n+ADMIN_EMAIL=devsenior477@gmail.com\r\n+ADMIN_PASS=tjic mjuq nlub euyd\n\\ No newline at end of file\n"
                },
                {
                    "date": 1756753540885,
                    "content": "Index: \n===================================================================\n--- \n+++ \n@@ -1,20 +1,5 @@\n PORT=5000\r\n-MONGO_URI=mongodb://localhost:27017/mvp\r\n+MONGO_URI=mongodb+srv://exoessai123456_db_user:<db_password>@cluster0.4cyqaml.mongodb.net/?retryWrites=true&w=majority&appName=Cluster0\r\n JWT_SECRET=your_jwt_secret\r\n ADMIN_EMAIL=devsenior477@gmail.com\r\n-ADMIN_PASS=tjic mjuq nlub euyd\n-PORT=5000\r\n-MONGO_URI=mongodb://localhost:27017/mvp\r\n-JWT_SECRET=your_jwt_secret\r\n-ADMIN_EMAIL=devsenior477@gmail.com\r\n-ADMIN_PASS=\n-PORT=5000\r\n-MONGO_URI=mongodb://localhost:27017/mvp\r\n-JWT_SECRET=your_jwt_secret\r\n-ADMIN_EMAIL=devsenior@gmail.com\r\n-ADMIN_PASS=abcdefgijklmnop\n-PORT=5000\r\n-MONGO_URI=mongodb://localhost:27017/mvp\r\n-JWT_SECRET=your_jwt_secret\r\n-ADMIN_EMAIL=yourgmail@gmail.com\r\n\\ No newline at end of file\n-ADMIN_PASS=abcdefgijklmnop\n+ADMIN_PASS=tjicmjuqnlubeuyd\n\\ No newline at end of file\n"
                },
                {
                    "date": 1756753552569,
                    "content": "Index: \n===================================================================\n--- \n+++ \n@@ -1,5 +1,5 @@\n PORT=5000\r\n-MONGO_URI=mongodb+srv://exoessai123456_db_user:<db_password>@cluster0.4cyqaml.mongodb.net/?retryWrites=true&w=majority&appName=Cluster0\r\n+MONGO_URI=mongodb+srv://exoessai123456_db_user:<>@cluster0.4cyqaml.mongodb.net/?retryWrites=true&w=majority&appName=Cluster0\r\n JWT_SECRET=your_jwt_secret\r\n ADMIN_EMAIL=devsenior477@gmail.com\r\n ADMIN_PASS=tjicmjuqnlubeuyd\n\\ No newline at end of file\n"
                },
                {
                    "date": 1756753582236,
                    "content": "Index: \n===================================================================\n--- \n+++ \n@@ -1,5 +1,5 @@\n PORT=5000\r\n-MONGO_URI=mongodb+srv://exoessai123456_db_user:<>@cluster0.4cyqaml.mongodb.net/?retryWrites=true&w=majority&appName=Cluster0\r\n+MONGO_URI=mongodb+srv://exoessai123456_db_user:<Qwertyuiop123@>@cluster0.4cyqaml.mongodb.net/?retryWrites=true&w=majority&appName=Cluster0\r\n JWT_SECRET=your_jwt_secret\r\n ADMIN_EMAIL=devsenior477@gmail.com\r\n ADMIN_PASS=tjicmjuqnlubeuyd\n\\ No newline at end of file\n"
                },
                {
                    "date": 1756753915890,
                    "content": "Index: \n===================================================================\n--- \n+++ \n@@ -1,5 +1,5 @@\n PORT=5000\r\n-MONGO_URI=mongodb+srv://exoessai123456_db_user:<Qwertyuiop123@>@cluster0.4cyqaml.mongodb.net/?retryWrites=true&w=majority&appName=Cluster0\r\n+MONGO_URI=mongodb+srv://exoessai123456_db_user:MyPass2025!@cluster0.4cyqaml.mongodb.net/mvpdb?retryWrites=true&w=majority&appName=Cluster0\r\n JWT_SECRET=your_jwt_secret\r\n ADMIN_EMAIL=devsenior477@gmail.com\r\n ADMIN_PASS=tjicmjuqnlubeuyd\n\\ No newline at end of file\n"
                },
                {
                    "date": 1756753921882,
                    "content": "Index: \n===================================================================\n--- \n+++ \n@@ -1,5 +1,5 @@\n PORT=5000\r\n-MONGO_URI=mongodb+srv://exoessai123456_db_user:MyPass2025!@cluster0.4cyqaml.mongodb.net/mvpdb?retryWrites=true&w=majority&appName=Cluster0\r\n+MONGO_URI=mongodb+srv://exoessai123456_db_user:!@cluster0.4cyqaml.mongodb.net/mvpdb?retryWrites=true&w=majority&appName=Cluster0\r\n JWT_SECRET=your_jwt_secret\r\n ADMIN_EMAIL=devsenior477@gmail.com\r\n ADMIN_PASS=tjicmjuqnlubeuyd\n\\ No newline at end of file\n"
                },
                {
                    "date": 1756753927732,
                    "content": "Index: \n===================================================================\n--- \n+++ \n@@ -1,5 +1,5 @@\n PORT=5000\r\n-MONGO_URI=mongodb+srv://exoessai123456_db_user:!@cluster0.4cyqaml.mongodb.net/mvpdb?retryWrites=true&w=majority&appName=Cluster0\r\n+MONGO_URI=mongodb+srv://exoessai123456_db_user:Qwertyuiop123!@cluster0.4cyqaml.mongodb.net/mvpdb?retryWrites=true&w=majority&appName=Cluster0\r\n JWT_SECRET=your_jwt_secret\r\n ADMIN_EMAIL=devsenior477@gmail.com\r\n ADMIN_PASS=tjicmjuqnlubeuyd\n\\ No newline at end of file\n"
                },
                {
                    "date": 1756754004688,
                    "content": "Index: \n===================================================================\n--- \n+++ \n@@ -1,5 +1,5 @@\n PORT=5000\r\n-MONGO_URI=mongodb+srv://exoessai123456_db_user:Qwertyuiop123!@cluster0.4cyqaml.mongodb.net/mvpdb?retryWrites=true&w=majority&appName=Cluster0\r\n+MONGO_URI=mongodb+srv://exoessai123456_db_user:Qwertyuiop123%40!@cluster0.4cyqaml.mongodb.net/mvpdb?retryWrites=true&w=majority&appName=Cluster0\r\n JWT_SECRET=your_jwt_secret\r\n ADMIN_EMAIL=devsenior477@gmail.com\r\n ADMIN_PASS=tjicmjuqnlubeuyd\n\\ No newline at end of file\n"
                },
                {
                    "date": 1756754995660,
                    "content": "Index: \n===================================================================\n--- \n+++ \n@@ -1,5 +1,5 @@\n PORT=5000\r\n-MONGO_URI=mongodb+srv://exoessai123456_db_user:Qwertyuiop123%40!@cluster0.4cyqaml.mongodb.net/mvpdb?retryWrites=true&w=majority&appName=Cluster0\r\n+MONGO_URI=mongodb+srv://exoessai123456_db_user:Test1234@cluster0.4cyqaml.mongodb.net/mvpdb?retryWrites=true&w=majority\r\n JWT_SECRET=your_jwt_secret\r\n ADMIN_EMAIL=devsenior477@gmail.com\r\n ADMIN_PASS=tjicmjuqnlubeuyd\n\\ No newline at end of file\n"
                },
                {
                    "date": 1756755153308,
                    "content": "Index: \n===================================================================\n--- \n+++ \n@@ -1,5 +1,5 @@\n PORT=5000\r\n-MONGO_URI=mongodb+srv://exoessai123456_db_user:Test1234@cluster0.4cyqaml.mongodb.net/mvpdb?retryWrites=true&w=majority\r\n+MONGO_URI=mongodb+srv://exoessai123456_db_user:admin123@cluster0.4cyqaml.mongodb.net/mvpdb?retryWrites=true&w=majority\r\n JWT_SECRET=your_jwt_secret\r\n ADMIN_EMAIL=devsenior477@gmail.com\r\n ADMIN_PASS=tjicmjuqnlubeuyd\n\\ No newline at end of file\n"
                },
                {
                    "date": 1757007243463,
                    "content": "Index: \n===================================================================\n--- \n+++ \n@@ -1,5 +1,5 @@\n PORT=5000\r\n MONGO_URI=mongodb+srv://exoessai123456_db_user:admin123@cluster0.4cyqaml.mongodb.net/mvpdb?retryWrites=true&w=majority\r\n JWT_SECRET=your_jwt_secret\r\n-ADMIN_EMAIL=devsenior477@gmail.com\r\n+ADMIN_EMAIL=@gmail.comdevsenior477\r\n ADMIN_PASS=tjicmjuqnlubeuyd\n\\ No newline at end of file\n"
                }
            ],
            "date": 1751212334419,
            "name": "Commit-0",
            "content": "PORT=5000\r\nMONGO_URI=mongodb://localhost:27017/admin-auth\r\nJWT_SECRET=your_jwt_secret"
        }
    ]
}